anbimapi.py
anbimapi-0.1.0.dist-info/WHEEL
anbimapi-0.1.0.dist-info/METADATA
anbimapi-0.1.0.dist-info/RECORD
