Metadata-Version: 2.1
Name: anbimapi
Version: 0.1.0
Summary: 
License: MIT
Author: Vinicius Mesel
Author-email: bioinfo.vinicius@gmail.com
Requires-Python: >=3.10,<4.0
Classifier: License :: OSI Approved :: MIT License
Classifier: Programming Language :: Python :: 3
Classifier: Programming Language :: Python :: 3.10
Requires-Dist: pandas (>=1.4.3,<2.0.0)
Requires-Dist: requests (>=2.28.1,<3.0.0)
